zbmain/__init__.py
zbmain/cls/__init__.py
zbmain/cls/singleton.py
zbmain/datasets/__init__.py
zbmain/datasets/dataset.py
zbmain/losses/__init__.py
zbmain/models/__init__.py
zbmain/models/tf_gru.py
zbmain/optimizers/__init__.py
zbmain/utils/__init__.py
zbmain/utils/args.py
zbmain/utils/config.py
zbmain/utils/file.py
zbmain/utils/network.py
zbmain/utils/onehot.py
zbmain/utils/path.py
zbmain/utils/robot.py
zbmain/utils/string.py
zbmain/utils/time.py
zbmain/utils/tools.py
zbmain/utils/translate.py
zbmain-0.0.9.dist-info/LICENSE
zbmain-0.0.9.dist-info/METADATA
zbmain-0.0.9.dist-info/WHEEL
zbmain-0.0.9.dist-info/top_level.txt
zbmain-0.0.9.dist-info/zip-safe
zbmain-0.0.9.dist-info/RECORD
